d3dshot/__init__.py
d3dshot/capture_output.py
d3dshot/capture_outputs/__init__.py
d3dshot/capture_outputs/numpy_capture_output.py
d3dshot/capture_outputs/numpy_float_capture_output.py
d3dshot/capture_outputs/pil_capture_output.py
d3dshot/capture_outputs/pytorch_capture_output.py
d3dshot/capture_outputs/pytorch_float_capture_output.py
d3dshot/capture_outputs/pytorch_float_gpu_capture_output.py
d3dshot/capture_outputs/pytorch_gpu_capture_output.py
d3dshot/d3dshot.py
d3dshot/display.py
d3dshot/dll/__init__.py
d3dshot/dll/d3d.py
d3dshot/dll/dxgi.py
d3dshot/dll/shcore.py
d3dshot/dll/user32.py
ok_d3dshot-0.1.5.dist-info/LICENSE
ok_d3dshot-0.1.5.dist-info/METADATA
ok_d3dshot-0.1.5.dist-info/WHEEL
ok_d3dshot-0.1.5.dist-info/RECORD
