Metadata-Version: 2.1
Name: ok-d3dshot
Version: 0.1.5
Summary: Extremely Fast and Robust Screen Capture on Windows with the Desktop Duplication API
Home-page: https://github.com/ok-oldking/D3DShot
License: MIT
Keywords: Screen Capture,Screenshot,Computer Vision,Windows
Author: Nicholas Brochu
Author-email: nicholas@serpent.ai
Requires-Python: >=3.6
Classifier: Development Status :: 5 - Production/Stable
Classifier: Intended Audience :: Developers
Classifier: License :: OSI Approved :: MIT License
Classifier: Natural Language :: English
Classifier: Operating System :: Microsoft :: Windows
Classifier: Operating System :: Microsoft :: Windows :: Windows 10
Classifier: Operating System :: Microsoft :: Windows :: Windows 8.1
Classifier: Programming Language :: Python
Classifier: Programming Language :: Python :: 3
Classifier: Programming Language :: Python :: 3.6
Classifier: Programming Language :: Python :: 3.7
Classifier: Programming Language :: Python :: 3.8
Classifier: Programming Language :: Python :: 3.9
Classifier: Programming Language :: Python :: 3.10
Classifier: Programming Language :: Python :: 3.11
Classifier: Programming Language :: Python :: 3.12
Classifier: Topic :: Multimedia :: Graphics
Classifier: Topic :: Multimedia :: Graphics :: Capture
Classifier: Topic :: Multimedia :: Graphics :: Capture :: Screen Capture
Requires-Dist: comtypes (>=1.1.7)
Requires-Dist: pillow (>=7.1.2)
Project-URL: Repository, https://github.com/ok-oldking/D3DShot
